coinglass_api/__init__.py
coinglass_api/api.py
coinglass_api/exceptions.py
coinglass_api/parameters.py
coinglass_api-1.3.0.dist-info/LICENSE.md
coinglass_api-1.3.0.dist-info/METADATA
coinglass_api-1.3.0.dist-info/WHEEL
coinglass_api-1.3.0.dist-info/RECORD
