Metadata-Version: 2.1
Name: coinglass-api
Version: 1.3.0
Summary: Unofficial Python client for Coinglass API
Home-page: https://github.com/dineshpinto/coinglass-api
License: MIT
Keywords: coinglass,api,crypto,cryptocurrency,bitcoin,ethereum,binance,dydx,okex
Author: dineshpinto
Author-email: annual.fallout_0z@gmail.com
Requires-Python: >=3.10,<4.0
Classifier: License :: OSI Approved :: MIT License
Classifier: Programming Language :: Python :: 3
Classifier: Programming Language :: Python :: 3.10
Classifier: Programming Language :: Python :: 3.11
Requires-Dist: pandas (>=2.0.0,<3.0.0)
Requires-Dist: pyzmq (>=25.1.1,<26.0.0)
Requires-Dist: requests (>=2.28.2,<3.0.0)
Project-URL: Repository, https://github.com/dineshpinto/coinglass-api
